{
    "1507535881730": {
        "game": "Ghost Knight Victis",
        "name": "Anomalous Underdog",
        "tools": "Unity, Blender, Substance Painter, Photoshop CC",
        "web": "hypertensiongamedev.tumblr.com",
        "wildcard": "ghost",
        "scoring": "1473 [x10.0] - 39 streak",
        "ext": ".jpg",
        "progress": [
            "+ fully implemented spear impale attack: enemies break free once their stamina is full, but the spear will break earlier if you attack the impaled enemy too much",
            "+ added more particle effects to the spear impale attack"
        ]
    },
    "1507540906061": {
        "game": "Mech game blabla",
        "name": "Tomo ge",
        "tools": "UE4, Blender, Krita",
        "web": "",
        "wildcard": "ghost",
        "scoring": "227 [x7.0] - 13 streak",
        "ext": ".jpg",
        "progress": [
            "+ Reworked the missile homing, they now home back onto their target if they miss, instead of getting stuck in a circle",
            "+ Multi-locking system for firing volleys of missile towards multiple enemies",
            "+ Changed how hit stops work",
            "+ Small input buffer",
            "- was sick for part of the week, busy with school for the other, less progress than expected$",
            "- \"worked\" on visuals again",
            "- HDD really about to fail"
        ]
    },
    "1507542528964": {
        "game": "Khryse",
        "name": "Khryse-dev",
        "tools": "UE4",
        "web": "https://khryse-dev.tumblr.com/ https://twitter.com/khryse_dev",
        "wildcard": "bat",
        "scoring": "130 [x5.0] - 9 streak",
        "ext": ".jpg",
        "progress": [
            "+ Added AI",
            "+ enemies will track you, lose you, try to kill you and return to their spawn point",
            "+ enemies will get hit ministuns and will get stunned from big damage",
            "+ added customizable hitboxes and refined the way combos and animations work"
        ]
    },
    "1507542960097": {
        "game": "Good Night, Knight",
        "name": "Knightdev",
        "tools": "GM:S, Aseprite",
        "web": "http://knightdev.tumblr.com/",
        "wildcard": "pumpkin",
        "scoring": "103 [x3.0] - 5 streak",
        "ext": ".png",
        "progress": [
            "+ Ability for pots to hold liquids",
            "+ Ability to flip pots 90 degrees",
            "+ Ability to fill up pots at pools directly",
            "+ Ability to dump pots contents out",
            "+ Some more cleaning up on the grabbing/throwing code"
        ]
    },
    "1507543221977": {
        "game": "Sweet Fukushu",
        "name": "LK",
        "tools": "Monogame",
        "web": "https://twitter.com/LKTheDev",
        "wildcard": "pumpkin",
        "scoring": "71 [x4.0] - 7 streak",
        "ext": ".png",
        "progress": [
            "+ Added controller support",
            "+ Started to work on two maps, a forest and a town section",
            "+ Gave the player the ability to crouch ",
            "- Using the sword with the controller doesn't feel good. The sword use really doesn't translate well to joystick."
        ]
    },
    "1507546084461": {
        "game": "Petite Witches",
        "name": "Dwarfdev",
        "tools": "Godot, Krita",
        "web": "https://twitter.com/DwarfDev",
        "wildcard": "pumpkin",
        "scoring": "74 [x1.0]",
        "ext": ".jpg",
        "progress": [
            "+ new inventory graphics",
            "+ rewrite status/inventory screens"
        ]
    },
    "1507546899630": {
        "game": "Bullet Hell Lane Shooter",
        "name": "ADMAN",
        "tools": "Unity, Blender",
        "web": "https://sgtadman.itch.io/untitled-bullet-hell-game",
        "wildcard": "bat",
        "scoring": "723 [x10.0] - 24 streak",
        "ext": ".jpg",
        "progress": [
            "+ Almost done with the reworking.",
            "- Probably have to build a new system for storing information about each wave, but that's probably not too difficult."
        ]
    },
    "1507547613578": {
        "game": "Project Blue Rose",
        "name": "Hessra",
        "tools": "GameMaker, Clipstudio",
        "web": "https://projectbluerose.tumblr.com/",
        "wildcard": "ghost",
        "scoring": "17 [x2.0] - 3 streak",
        "ext": ".png",
        "progress": [
            "+ More progress on the backgrounds",
            "+ Running animation finished",
            "+ Actually working healthbar",
            "+ Redrew old sprites, pretty much everything is on the same resolution now",
            "- Swamped in other work"
        ]
    },
    "1507550780330": {
        "game": "Devil Engine",
        "name": "shmoopdev",
        "tools": "GMS,Photoshop,aesprite",
        "web": "shmoopdev.tumblr.com/",
        "wildcard": "ghost",
        "scoring": "1273 [x10.0] - 35 streak",
        "ext": ".png",
        "progress": [
            "+ Stage 3 patterns mostly done",
            "+ Boss animation done",
            "+ Boss pattern around half done",
            "+ Fixed the laser doing either way to much damage or not enough depending on how the button was fanned",
            "- Bits of the pattern were repetitive/not so they're gone",
            "- overall slow week"
        ]
    },
    "1507559305016": {
        "game": "dungeon antfarm",
        "name": "meatRay",
        "tools": "Monogame",
        "web": "http://www.meatRay.com",
        "wildcard": "bat",
        "scoring": "10 [x1.0]",
        "ext": ".png",
        "progress": [
            "+ Rendering in 3D!",
            "+ Implemented a \"lazy\" pathfinding solution",
            "+ Implemented more behaivours",
            "+ Began working on team-manager AI, and win/loss",
            "- Working too much, so no dev time",
            "- Now I need to do 3D models and I suck at it",
            "- Now I need to animated and I suck at it"
        ]
    },
    "1507561723452": {
        "game": "The Jackal",
        "name": "AngryGhoust",
        "tools": "Game Maker 1.4, Paint.NET, SAI",
        "web": "https://angryghoust.tumblr.com",
        "wildcard": "ghost",
        "scoring": "39 [x3.0] - 5 streak",
        "ext": ".png",
        "progress": [
            "+ More work on the portraits",
            "+ Worked on a first boss sprite",
            "+ Implemented a new enemy",
            "+ Worked on the story a bit"
        ]
    },
    "1507562627657": {
        "game": "Nox Striga",
        "name": "Mez",
        "tools": "Unity, Blender, Paint.Net, Gimp",
        "web": "mezdritch (twitter/tumblr)",
        "wildcard": "pumpkin",
        "scoring": "426 [x9.5] - 18 streak",
        "ext": ".png",
        "progress": [
            "+ Some UI changes and improvement.",
            "+ Worked on the overwold.",
            "+ Still redesigning the cards"
        ]
    },
    "1507563469696": {
        "game": "Cyberdetective 2042: Maximum Investigation",
        "name": "JacquesGuga",
        "tools": "GameMaker, CLIP Studio, Aseprite",
        "web": "gugajoke.tumblr.com/",
        "wildcard": "ghost",
        "scoring": "10 [x1.0]",
        "ext": ".png",
        "progress": [
            "+ remade the map and some of the UI",
            "+ lots of new dialog and overall story planning",
            "- slow week due to real-life duties etc",
            "- still no better name"
        ]
    },
    "1507570978632": {
        "game": "MoGiSho (Moth Girl Shooter)",
        "name": "WRIT",
        "tools": "GMS",
        "web": "http://thirdkeyofsun.tumblr.com/, https://twitter.com/ThirdKeyOfSun",
        "wildcard": "pumpkin",
        "scoring": "289 [x1.0]",
        "ext": ".png",
        "progress": [
            "+ Implemented burst selection for Lore",
            "+ Reintroduced moth dust bombing for Type B",
            "+ Working on spirit art type selection",
            "- Lots of animation and art to do before DD17",
            "- Redesigning stages from scratch feels bad but is necessary"
        ]
    },
    "1507571021134": {
        "game": "UP 2-3",
        "name": "SageOne",
        "tools": "Game Maker Studio",
        "web": "https://sageone.itch.io/up2-3",
        "wildcard": "ghost",
        "scoring": "5 [x1.0]",
        "ext": ".png",
        "progress": [
            "+ core puzzle and 5 difficulty levels",
            "+ main, settings and credits screens",
            "+ added animated background",
            "+ added some music and UI sounds",
            "- temporarily removed resolution change due to scaling fuckups"
        ]
    },
    "1507572400854": {
        "game": "Scrap Galaxy",
        "name": "J3X",
        "tools": "Unity 3D",
        "web": "scrapgalaxy.com",
        "wildcard": "ghost",
        "scoring": "10 [x1.0]",
        "ext": ".jpg",
        "progress": [
            "+ Fixed several bugs in introduction level.",
            "+ Managed to upload game to Steam.",
            "+ Filled in some more things on the Store page.",
            "+ Fixed tickets to game conference and booth.",
            "- Need to drop some features for release."
        ]
    },
    "1507575141387": {
        "game": "Galactic Pocket Billiards",
        "name": "Sirrico-Net Games",
        "tools": "GMS",
        "web": "https://sirrico.itch.io",
        "wildcard": "bat",
        "scoring": "10 [x1.0]",
        "ext": ".png",
        "progress": [
            "+ Released demo! Leave me some feedback please",
            "+ New cover art",
            "+ Added speed slider (to be released in next demo)",
            "+ Changed some colors around (same as above)",
            "- Nobody is downloading and giving me their thoughts"
        ]
    },
    "1507581924157": {
        "game": "Horror JRPG",
        "name": "LoneBuckshot",
        "tools": "Unity",
        "web": "https://twitter.com/LoneBuckshot & https://lonebuckshot.tumblr.com/",
        "wildcard": "pumpkin",
        "scoring": "71 [x4.0] - 7 streak",
        "ext": ".jpg",
        "progress": [
            "+ Buff/Debuff system implemented, pending testing",
            "+ Each unit can have a default attack effect, and multiple spell effects",
            "+ Added a new enemy",
            "+ Added new default attack effect",
            "+ Tweaking camera tilt/zoom when units attack and cast spells",
            "+ Replaced all placeholder skill/status icons",
            "+ Battle system debugging"
        ]
    },
    "1507585896038": {
        "game": "Kick-in'",
        "name": "Kickindev",
        "tools": "GM:S",
        "web": "kickindev.tumblr.com",
        "wildcard": "bat",
        "scoring": "973 [x10.0] - 29 streak",
        "ext": ".png",
        "progress": [
            "+ Game now runs in 16:9 resolution instead of 4:3, making the game upscale correctly on most modern screens.",
            "+ Tonfa hitbox scripting complete",
            "+ Tonfa dazed states complete",
            "+ Fighting ring made wider and fighting ring code simplified",
            "+ Had a more productive week than expected in general"
        ]
    },
    "1507587595327": {
        "game": "UW",
        "name": "anon",
        "tools": "Unity",
        "web": "",
        "wildcard": "ghost",
        "scoring": "17 [x2.0] - 3 streak",
        "ext": ".jpg",
        "progress": [
            "+ Rifle and knife added",
            "+ Blood splash added",
            "+ Cover to Cover AI behavior",
            "+ Retreat option when encountered enemy",
            "+ Character skills(+UI for it)",
            "+ UI Improved(Button & some BGI)",
            "+ Training WIP",
            "- Artist is hard to find"
        ]
    },
    "1507588081925": {
        "game": "Storm Storm",
        "name": "Dogma",
        "tools": "Assembly",
        "web": "https://twitter.com/CaptDreamcast",
        "wildcard": "bat",
        "scoring": "5 [x1.0]",
        "ext": ".png",
        "progress": [
            "+ Added throwing the anti storm storm ball with your paddle",
            "+ About to drop the greatest meme trailer humanity ever dared to witness",
            "- Gamedev progress screeched to a halt since last Thursday"
        ]
    },
    "1507592881026": {
        "game": "Unnamed Pixel Platformer",
        "name": "Anonymous",
        "tools": "C++, Code::Blocks, SDL2, Aseprite, Tiled",
        "web": "N/A",
        "wildcard": "bat",
        "scoring": "54 [x2.5] - 4 streak",
        "ext": ".png",
        "progress": [
            "+ More work on the special attacks",
            "+ Some optimizations for ground collision testing",
            "+ Workaround for a strange driver bug for a snes controller adapter in linux",
            "- Need to come up with a better way to generate mappings for unsupported controllers",
            "- The same adapter doesn't work at all in windows"
        ]
    },
    "1507592949429": {
        "game": "Cash Sample",
        "name": "SlowDancer",
        "tools": "RPG Maker MV, Photofiltre, Cubase 8, Internet, Coke",
        "web": "https://lemmyrodul.com",
        "wildcard": "ghost",
        "scoring": "39 [x3.0] - 5 streak",
        "ext": ".png",
        "progress": [
            "+ Working on GFX via a Jam Game until nov 9",
            "+ Working on eventing via a Jam Game until nov 9",
            "- There's no skeleton theme for the recap"
        ]
    },
    "1507594362543": {
        "game": "Gunsun Zeros",
        "name": "GearSting",
        "tools": "UE4, Blender, Paint.net",
        "web": "gearsting.tumblr.com",
        "wildcard": "bat",
        "scoring": "40 [x1.5] - 2 streak",
        "ext": ".png",
        "progress": [
            "+ made a deployable Sentry Gun",
            "+ reworked some of the enemy targeting so they can shoot the sentries",
            "- getting smashed by work"
        ]
    },
    "1507605903235": {
        "game": "Within the Green",
        "name": "Anon",
        "tools": "Unity, gimp",
        "web": "https://teamsolotent.tumblr.com/",
        "wildcard": "ghost",
        "scoring": "227 [x7.0] - 13 streak",
        "ext": ".png",
        "progress": [
            "+ planning better enemy ai",
            "+ slowly make art assets",
            "- slowly"
        ]
    },
    "1507606152836": {
        "game": "Sudokube",
        "name": "Blank",
        "tools": "Unity",
        "web": "@PhilBlankGames",
        "wildcard": "pumpkin",
        "scoring": "165 [x6.0] - 11 streak",
        "ext": ".png",
        "progress": [
            "+ Rewrote controls to be less horrible",
            "+ Basic anti-cheat logic for leaderboards",
            "- However I lost millisecond precision for the leaderbord because Steam server only returns UTC time",
            "+ Minor bug fixes",
            "- My game has no visible progress from now until release except for when I replace the UI",
            "- No idea how I'm going to market this aside from the basics"
        ]
    },
    "1507610184936": {
        "game": "Skylarks",
        "name": "Mako",
        "tools": "Rust, Logic, Blender",
        "web": "http://mako.itch.io/skylarks",
        "wildcard": "pumpkin",
        "scoring": "1593 [x10.0] - 63 streak",
        "ext": ".png",
        "progress": [
            "+ Got the new renderer working",
            "+ Replaced my custom GUI shit with an existing library",
            "+ Made the renderer play nice with the new GUI toolkit",
            "+ Rewrote the core runloop to use an explicit scene stack",
            "+ Refactored some stuff into separate libraries",
            "+ Refactored the map view into a reusable GUI widget",
            "- Mouse clicks are being handled by the wrong widget and I don't know why"
        ]
    },
    "1507613491171": {
        "game": "Vampire's Bit",
        "name": "VampireDev",
        "tools": "Game Maker, Photoshop",
        "web": "vampiredev.tumblr.com \u00b7 twitter.com/jcsvampire",
        "wildcard": "bat",
        "scoring": "108 [x1.0]",
        "ext": ".gif",
        "progress": [
            "+ Reworking a lot of code to test new features",
            "+ Working on new animations and misc. art stuff",
            "- I think bonus stage background ended looking too busy",
            "- Splitting time with side project"
        ]
    },
    "1507620272407": {
        "game": "Ctesiphon",
        "name": "Stomy",
        "tools": "C++/OpenGL, Blender, Krita",
        "web": "stomygame.tumblr.com",
        "wildcard": "pumpkin",
        "scoring": "315 [x6.0] - 11 streak",
        "ext": ".png",
        "progress": [
            "+ The C++ rewrite continues",
            "+ Got started on the static mesh and weapon systems"
        ]
    },
    "1507625206208": {
        "game": "Space Dementia",
        "name": "rez",
        "tools": "SFML/C++",
        "web": "rezydev.tumblr.com",
        "wildcard": "bat",
        "scoring": "517 [x3.5] - 6 streak",
        "ext": ".png",
        "progress": [
            "+ Contact damage can destroy tiles",
            "+ Tile regeneration",
            "+ More improvements and stage for a boss",
            "+ Jumping on higher platforms is tighter",
            "+ Dash doesn't get in the way with connecting jumps"
        ]
    },
    "1507628149956": {
        "game": "Thuby's Game",
        "name": "Thuby",
        "tools": "Unity, Aseprite.",
        "web": "https://twitter.com/xthuby",
        "wildcard": "pumpkin",
        "scoring": "20 [x1.5] - 2 streak",
        "ext": ".png",
        "progress": [
            "+ Changed the colour palette to the Dawnbringer 32 palette.",
            "+ Gave the enemy some nice animations.",
            "+ Started using Unity's new tiling system.",
            "- It's unfinished and complicated to script for it.",
            "- Scrapped the background.",
            "- Still don't know how to make good backgrounds."
        ]
    },
    "1507634037916": {
        "game": "Sim Loli",
        "name": "Anon",
        "tools": "C++",
        "web": "/agdg/26682",
        "wildcard": "pumpkin",
        "scoring": "27 [x2.0] - 3 streak",
        "ext": ".png",
        "progress": [
            "+ Went through all palettes for eyes/hair/body and made them better + implemented ones that weren't there before",
            "+ general art improvements",
            "+ dress clothes",
            "+ Added in a kindergartner sized portrait",
            "+ Added in a system for portrait-offsets to minimize amount of work needed for kidnergartner/middleschooler portraits"
        ]
    },
    "1507635386994": {
        "game": "Bunny Game",
        "name": "Anon",
        "tools": "Love2d",
        "web": "",
        "wildcard": "bat",
        "scoring": "5 [x1.0]",
        "ext": ".png",
        "progress": [
            "+ Started project",
            "+ Player animation and movement",
            "+ Tileset and map loading",
            "+ Automatic tiling"
        ]
    },
    "1507648235154": {
        "game": "Harmon:i:c",
        "name": "AWK",
        "tools": "Godot",
        "web": "https://awk.itch.io/harmonic, https://twitter.com/AWKgamedev, https://awkgamedev.tumblr.com/",
        "wildcard": "ghost",
        "scoring": "823 [x10.0] - 26 streak",
        "ext": ".png",
        "progress": [
            "+ Kinda finished Level 1-2, didn't test it extensively yet",
            "+ Ported old Level 1-2 (now 1-3) since I liked it, I will probably put the other old levels in some kind of hard mode extra chapter and make new ones with a smoother difficulty curve since that was the main complaint, still trying to figure out what a good curve is",
            "+ Added player step and swipe sounds",
            "+ The experimental module system I made (pic related) is working out fine so far",
            "+ Moved a few variables around to a singleton, wow"
        ]
    },
    "1507652085529": {
        "game": "Unknown World",
        "name": "dewdneym",
        "tools": "RPG Maker VX Ace, Paint.net",
        "web": "dewdneym.tumblr.com, https://twitter.com/UnknownWorldDev",
        "wildcard": "pumpkin",
        "scoring": "47 [x2.5] - 4 streak",
        "ext": ".png",
        "progress": [
            "+ (mostly) completed sidequest I put on the backburner. Can't do the dance cutscene until music is made for it.",
            "+ created some new enemy sprites",
            "= Halfway finished with promo art",
            "- not working hard enough"
        ]
    }
}